LICENSE
README.md
setup.py
dataset/__init__.py
dataset/dataset.py
dataset/utils.py
trialbench/__init__.py
trialbench/dataset.py
trialbench/function.py
trialbench/metrics.py
trialbench/utils.py
trialbench.egg-info/PKG-INFO
trialbench.egg-info/SOURCES.txt
trialbench.egg-info/dependency_links.txt
trialbench.egg-info/requires.txt
trialbench.egg-info/top_level.txt
trialbench/data/sentence2embedding.pkl
trialbench/data/ADMET/cooked/absorption_train.txt
trialbench/data/ADMET/cooked/absorption_valid.txt
trialbench/data/ADMET/cooked/distribution_train.txt
trialbench/data/ADMET/cooked/distribution_valid.txt
trialbench/data/ADMET/cooked/excretion_train.txt
trialbench/data/ADMET/cooked/excretion_valid.txt
trialbench/data/ADMET/cooked/metabolism_train.txt
trialbench/data/ADMET/cooked/metabolism_valid.txt
trialbench/data/ADMET/cooked/toxicity_train.txt
trialbench/data/ADMET/cooked/toxicity_valid.txt
trialbench/data/mesh-embeddings/LICENSE
trialbench/data/mesh-embeddings/README.md
trialbench/data/mesh-embeddings/edgelist.txt.gz
trialbench/data/mesh-embeddings/mesh_embeddings.txt.gz
trialbench/data/mesh-embeddings/mesh_ui_to_id.pickle
trialbench/data/mesh-embeddings/term_to_ui.pkl
trialbench/models/__init__.py
trialbench/models/gnn_layers.py
trialbench/models/icdcode_encode.py
trialbench/models/mesh_encode.py
trialbench/models/model_multi.py
trialbench/models/module.py
trialbench/models/molecule_encode.py
trialbench/models/protocol_encode.py
trialbench/models/tabular_encode.py
trialbench/models/text_encode.py