Metadata-Version: 2.4
Name: trialbench
Version: 0.3.0
Summary: A multimodal AI-Ready Dataset. Updated Regularly. More details from TrialBench: Multi-Modal AI-Ready Datasets for Clinical Trial Prediction.
Home-page: https://github.com/ML2Health/ML2ClinicalTrials/tree/main
Author: authors of 
License: MIT
Classifier: Programming Language :: Python
Classifier: Programming Language :: Python :: 3
Classifier: Programming Language :: Python :: 3.6
Classifier: Programming Language :: Python :: Implementation :: CPython
Classifier: Programming Language :: Python :: Implementation :: PyPy
Requires-Python: >=3.6.0
License-File: LICENSE
Requires-Dist: numpy>=1.20
Requires-Dist: scikit-learn>=0.20.0
Requires-Dist: pandas>=1.3
Requires-Dist: category_encoders>=2.6.3
Requires-Dist: icd10-cm>=0.0.5
Requires-Dist: matplotlib>=3.5.3
Requires-Dist: rdkit==2024.9.6
Requires-Dist: requests>=2.31.0
Requires-Dist: sparsemax>=0.1.9
Requires-Dist: torch<=2.0.0,>=1.13.1
Requires-Dist: tqdm>=4.66.4
Dynamic: author
Dynamic: classifier
Dynamic: description
Dynamic: description-content-type
Dynamic: home-page
Dynamic: license
Dynamic: license-file
Dynamic: requires-dist
Dynamic: requires-python
Dynamic: summary
